pytest_rst.py
pytest_rst-0.1.5.dist-info/WHEEL
pytest_rst-0.1.5.dist-info/entry_points.txt
pytest_rst-0.1.5.dist-info/COPYING
pytest_rst-0.1.5.dist-info/METADATA
pytest_rst-0.1.5.dist-info/RECORD
