Metadata-Version: 2.1
Name: pytest-rst
Version: 0.1.5
Summary: Test code from RST documents with pytest
Home-page: https://github.com/mosquito/pytest-rst
License: MIT
Keywords: pytest,rst,ReStructuredText,documentation
Author: Dmitry Orlov
Author-email: me@mosquito.su
Requires-Python: >=3.7,<4.0
Classifier: Framework :: Pytest
Classifier: Intended Audience :: Developers
Classifier: License :: OSI Approved :: MIT License
Classifier: Natural Language :: Russian
Classifier: Operating System :: MacOS
Classifier: Operating System :: POSIX
Classifier: Programming Language :: Python
Classifier: Programming Language :: Python :: 3
Classifier: Programming Language :: Python :: 3.7
Classifier: Programming Language :: Python :: 3.8
Classifier: Programming Language :: Python :: 3.9
Classifier: Programming Language :: Python :: 3.10
Classifier: Programming Language :: Python :: 3.11
Classifier: Programming Language :: Python :: 3
Classifier: Programming Language :: Python :: 3.10
Classifier: Programming Language :: Python :: 3.11
Classifier: Programming Language :: Python :: 3.7
Classifier: Programming Language :: Python :: 3.8
Classifier: Programming Language :: Python :: 3.9
Classifier: Programming Language :: Python :: Implementation :: CPython
Classifier: Topic :: Software Development
Classifier: Topic :: Software Development :: Libraries
Project-URL: Documentation, https://github.com/mosquito/pytest-rst/blob/master/README.rst
Project-URL: Source, https://github.com/mosquito/pytest-rst
Project-URL: Tracker, https://github.com/mosquito/pytest-rst/issues
